sql_query_builder.py
python_sql_query_builder-0.1.4.dist-info/licenses/LICENSE
python_sql_query_builder-0.1.4.dist-info/METADATA
python_sql_query_builder-0.1.4.dist-info/WHEEL
python_sql_query_builder-0.1.4.dist-info/top_level.txt
python_sql_query_builder-0.1.4.dist-info/RECORD
