Metadata-Version: 2.4
Name: python-sql-query-builder
Version: 0.1.4
Summary: A fluent Python SQL query builder with support for joins, where clauses, inserts, updates, and more
Author-email: Omer Menashe <unspecified@mail.com>
License: MIT
Project-URL: Source, https://github.com/iamomerm/python-sql-query-builder
Keywords: python-sql-query-builder,sql-query-builder,sql
Classifier: Programming Language :: Python :: 3
Classifier: License :: OSI Approved :: MIT License
Classifier: Operating System :: OS Independent
Classifier: Development Status :: 3 - Alpha
Classifier: Intended Audience :: Developers
Classifier: Topic :: Database :: Front-Ends
Requires-Python: >=3.7
License-File: LICENSE
Dynamic: license-file
